{"author":{"id":"MDQ6VXNlcjIyNDUwMTg4","is_bot":false,"login":"atomiks","name":""},"body":"This needs to be configurable for a couple of reasons:\r\n\r\n1. External links shouldn't close the menu, only client-side ones. Stripe and Apple leave theirs open as they act as external links.\r\n2. Nested menus shouldn't close their menu since they're meant to be always-open\r\n\r\nThis API matches regular `Menu` but `false` by default","labels":[{"id":"LA_kwDOLW-eZs8AAAABio8G3g","name":"type: bug","description":"It doesn't behave as expected.","color":"e11d21"},{"id":"LA_kwDOLW-eZs8AAAABio8W4A","name":"type: new feature","description":"Expand the scope of the product to solve a new problem.","color":"1F7BDA"},{"id":"LA_kwDOLW-eZs8AAAAB-TIAdw","name":"component: navigation menu","description":"Changes related to the navigation menu component.","color":"ffffff"}],"mergedAt":"2025-09-24T00:12:25Z","number":2740,"title":"[navigation menu] Make link close on click configurable"}
