{"url":"https://api.github.com/repos/mui/base-ui/issues/4402","repository_url":"https://api.github.com/repos/mui/base-ui","labels_url":"https://api.github.com/repos/mui/base-ui/issues/4402/labels{/name}","comments_url":"https://api.github.com/repos/mui/base-ui/issues/4402/comments","events_url":"https://api.github.com/repos/mui/base-ui/issues/4402/events","html_url":"https://github.com/mui/base-ui/issues/4402","id":4107769226,"node_id":"I_kwDOLW-eZs7015WK","number":4402,"title":"[drawer][toast] Support logical values for swipeDirection","user":{"login":"aarongarciah","id":7225802,"node_id":"MDQ6VXNlcjcyMjU4MDI=","avatar_url":"https://avatars.githubusercontent.com/u/7225802?v=4","gravatar_id":"","url":"https://api.github.com/users/aarongarciah","html_url":"https://github.com/aarongarciah","followers_url":"https://api.github.com/users/aarongarciah/followers","following_url":"https://api.github.com/users/aarongarciah/following{/other_user}","gists_url":"https://api.github.com/users/aarongarciah/gists{/gist_id}","starred_url":"https://api.github.com/users/aarongarciah/starred{/owner}{/repo}","subscriptions_url":"https://api.github.com/users/aarongarciah/subscriptions","organizations_url":"https://api.github.com/users/aarongarciah/orgs","repos_url":"https://api.github.com/users/aarongarciah/repos","events_url":"https://api.github.com/users/aarongarciah/events{/privacy}","received_events_url":"https://api.github.com/users/aarongarciah/received_events","type":"User","user_view_type":"public","site_admin":false},"labels":[{"id":6619629096,"node_id":"LA_kwDOLW-eZs8AAAABio-GKA","url":"https://api.github.com/repos/mui/base-ui/labels/component:%20drawer","name":"component: drawer","color":"ffffff","default":false,"description":"Changes related to the drawer component."},{"id":6621309265,"node_id":"LA_kwDOLW-eZs8AAAABiqkpUQ","url":"https://api.github.com/repos/mui/base-ui/labels/discussion","name":"discussion","color":"bfdadc","default":false,"description":""},{"id":6621343548,"node_id":"LA_kwDOLW-eZs8AAAABiqmvPA","url":"https://api.github.com/repos/mui/base-ui/labels/component:%20toast","name":"component: toast","color":"ffffff","default":false,"description":"Changes related to the toast component."}],"state":"open","locked":false,"assignees":[],"milestone":null,"comments":1,"created_at":"2026-03-20T13:03:27Z","updated_at":"2026-03-31T13:14:35Z","closed_at":null,"assignee":null,"author_association":"MEMBER","issue_field_values":[],"type":null,"active_lock_reason":null,"sub_issues_summary":{"total":0,"completed":0,"percent_completed":0},"issue_dependencies_summary":{"blocked_by":0,"total_blocked_by":0,"blocking":0,"total_blocking":0},"body":"# Discussion\n\nBoth [Drawer](https://base-ui.com/react/components/drawer#DrawerRoot-swipeDirection) and [Toast](https://base-ui.com/react/components/toast#ToastRoot-swipeDirection) have a `swipeDirection` prop. At the time of writing, `swipeDirection` supports these values: `'up'`, `'down'`, `'left'`, and `'right'`.\n\nGiven that Base UI already offers a [DirectionProvider](https://base-ui.com/react/utils/direction-provider) component for implementing RTL UIs, would it make sense to support `'inline-start'` and `'inline-end'` values for the `swipeDirection` prop so users don't need to manage it themselves? We already support logical values on the [`side`](https://base-ui.com/react/components/popover#PopoverPositioner-side) prop of Positioner parts like `Popover.Positioner`.","closed_by":null,"reactions":{"url":"https://api.github.com/repos/mui/base-ui/issues/4402/reactions","total_count":0,"+1":0,"-1":0,"laugh":0,"hooray":0,"confused":0,"heart":0,"rocket":0,"eyes":0},"timeline_url":"https://api.github.com/repos/mui/base-ui/issues/4402/timeline","performed_via_github_app":null,"state_reason":null,"pinned_comment":null}