{
  "name": "MeterTrack",
  "description": "Contains the meter indicator and represents the entire range of the meter.\nRenders a `<div>` element.",
  "props": {
    "className": {
      "type": "string | ((state: Meter.Root.State) => string | undefined)",
      "description": "CSS class applied to the element, or a function that\nreturns a class based on the component’s state.",
      "detailedType": "| string\n| ((state: Meter.Root.State) => string | undefined)"
    },
    "style": {
      "type": "CSSProperties | ((state: Meter.Root.State) => CSSProperties | undefined)",
      "detailedType": "| React.CSSProperties\n| ((state: Meter.Root.State) => CSSProperties | undefined)\n| undefined"
    },
    "render": {
      "type": "ReactElement | ((props: HTMLProps, state: Meter.Root.State) => ReactElement)",
      "description": "Allows you to replace the component’s HTML element\nwith a different tag, or compose it with another component.\n\nAccepts a `ReactElement` or a function that returns the element to render.",
      "detailedType": "| ReactElement\n| ((\n    props: HTMLProps,\n    state: Meter.Root.State,\n  ) => ReactElement)"
    }
  },
  "dataAttributes": {},
  "cssVariables": {}
}
