{
  "props": {
    "className": { "type": { "name": "union", "description": "func<br>&#124;&nbsp;string" } },
    "render": { "type": { "name": "union", "description": "element<br>&#124;&nbsp;func" } }
  },
  "name": "NumberFieldDecrement",
  "imports": [
    "import { NumberField } from '@base-ui-components/react/number-field';\nconst NumberFieldDecrement = NumberField.Decrement;"
  ],
  "classes": [],
  "spread": true,
  "themeDefaultProps": true,
  "muiName": "NumberFieldDecrement",
  "forwardsRefTo": "HTMLButtonElement",
  "filename": "/packages/react/src/number-field/decrement/NumberFieldDecrement.tsx",
  "inheritance": null,
  "demos": "<ul><li><a href=\"/components/react-number-field/\">Number Field</a></li></ul>",
  "cssComponent": false
}
