{
  "props": {
    "className": { "type": { "name": "union", "description": "func<br>&#124;&nbsp;string" } },
    "render": { "type": { "name": "union", "description": "element<br>&#124;&nbsp;func" } }
  },
  "name": "SliderControl",
  "imports": [
    "import { Slider } from '@base-ui-components/react/slider';\nconst SliderControl = Slider.Control;"
  ],
  "classes": [],
  "spread": true,
  "themeDefaultProps": true,
  "muiName": "SliderControl",
  "forwardsRefTo": "HTMLDivElement",
  "filename": "/packages/react/src/slider/control/SliderControl.tsx",
  "inheritance": null,
  "demos": "<ul><li><a href=\"/components/react-slider/\">Slider</a></li></ul>",
  "cssComponent": false
}
